gpulink/__init__.py
gpulink/__main__.py
gpulink/consts.py
gpulink/cli/__init__.py
gpulink/cli/cmd_record.py
gpulink/cli/cmd_sensors.py
gpulink/cli/console.py
gpulink/devices/__init__.py
gpulink/devices/base_device.py
gpulink/devices/device_mock.py
gpulink/devices/devicectx.py
gpulink/devices/gpu.py
gpulink/devices/nvml_defines.py
gpulink/devices/nvml_device.py
gpulink/devices/query.py
gpulink/plotting/__init__.py
gpulink/plotting/plot.py
gpulink/recording/__init__.py
gpulink/recording/gpu_recording.py
gpulink/recording/recorder.py
gpulink/recording/timeseries.py
gpulink/threading/__init__.py
gpulink/threading/stoppable_thread.py
gpulink-0.6.0.dist-info/LICENSE
gpulink-0.6.0.dist-info/METADATA
gpulink-0.6.0.dist-info/WHEEL
gpulink-0.6.0.dist-info/entry_points.txt
gpulink-0.6.0.dist-info/top_level.txt
gpulink-0.6.0.dist-info/RECORD
