Metadata-Version: 2.1
Name: gpulink
Version: 0.6.0
Summary: A simple tool for monitoring and displaying GPU stats
Home-page: https://github.com/PhilipKlaus/gpu-link
Author: Philip Klaus
Project-URL: Bug Tracker, https://github.com/PhilipKlaus/gpu-link/issues
Classifier: Programming Language :: Python :: 3
Classifier: License :: OSI Approved :: MIT License
Classifier: Operating System :: OS Independent
Requires-Python: >=3.7
License-File: LICENSE
Requires-Dist: pynvml ==11.5.0
Requires-Dist: matplotlib >=3.7.1
Requires-Dist: numpy >=1.24.3
Requires-Dist: tabulate >=0.9.0
Requires-Dist: colorama >=0.4.6
Requires-Dist: click >=8.1.3
Provides-Extra: test
Requires-Dist: pytest ; extra == 'test'
Requires-Dist: pytest-mock ; extra == 'test'
Requires-Dist: pytest-cov ; extra == 'test'
